hashequal/__init__.py
hashequal-1.0.2.dist-info/LICENSE
hashequal-1.0.2.dist-info/METADATA
hashequal-1.0.2.dist-info/WHEEL
hashequal-1.0.2.dist-info/top_level.txt
hashequal-1.0.2.dist-info/RECORD
