Metadata-Version: 2.1
Name: hashequal
Version: 1.0.2
Summary: A tool for quasi-interactive math sheets
Home-page: https://github.com/eevleevs/hashequal
Author: Giulio Malventi
Author-email: giulio.malventi@gmail.com
Project-URL: Bug Tracker, https://github.com/eevleevs/hashequal/issues
Classifier: Programming Language :: Python :: 3
Classifier: License :: OSI Approved :: Mozilla Public License 2.0 (MPL 2.0)
Classifier: Operating System :: OS Independent
Requires-Python: >=3.6
License-File: LICENSE
